README.md
setup.py
revshell/__init__.py
revshell/revshell.py
revshell.egg-info/PKG-INFO
revshell.egg-info/SOURCES.txt
revshell.egg-info/dependency_links.txt
revshell.egg-info/entry_points.txt
revshell.egg-info/top_level.txt