Metadata-Version: 1.0
Name: revshell
Version: 1.0.0
Summary: Reverse Python Shell
Home-page: UNKNOWN
Author: BrainDisassembly
Author-email: braindisassm@gmail.com
License: GPL v3
Platform: UNKNOWN
